google_tasks_to_ical/__init__.py
google_tasks_to_ical/main.py
google_tasks_to_ical-1.1.0.dist-info/LICENSES/Unlicense.txt
google_tasks_to_ical-1.1.0.dist-info/METADATA
google_tasks_to_ical-1.1.0.dist-info/WHEEL
google_tasks_to_ical-1.1.0.dist-info/entry_points.txt
google_tasks_to_ical-1.1.0.dist-info/RECORD
