Metadata-Version: 2.1
Name: google-tasks-to-ical
Version: 1.1.0
Summary: Converts Google Tasks JSON into iCal VTODO
Author: PATHFINDER
Author-email: pathfinder@pathfinderdreams.com
Requires-Python: >=3.12,<4.0
Classifier: Programming Language :: Python :: 3
Classifier: Programming Language :: Python :: 3.12
Requires-Dist: icalendar (>=5.0.11,<6.0.0)
